Workbook

Sheet Modelo de Costos y Precios
A1: UNIVERSIDAD DE GUADALAJARA | CENTRO UNIVERSITARIO DE TONALÁ
A2: DETERMINACIÓN DEL COSTO DE UN PRODUCTO O SERVICIO — PLATAFORMA SIGRE
A3: Alumno: Fierro Meléndez Ernesto Hatuey | Docente: Mtra. Abril Adriana Angulo Sherman | Materia: Formulación y Evaluación de Proyectos
A5: Materia prima / Insumos TI | B5: 100 pzas / dependencias | G5: Costo Total del Lote (100 pzas): | H5: =D11+C17+B25+B30
A6: Concepto | B6: Unidades | C6: CUnitario (sin iva) | D6: CTotal(+IVA) | E6: IVA | G6: Costo Unitario (1 pza de 100): | H6: =H5/100
A7: A (Instancias Cloud Run Compute) | B7: 2 | C7: 500 | D7: =B7*C7*1.16 | E7: =D7-B7*C7
A8: B (Base de Datos Cloud SQL PostgreSQL) | B8: 1 | C8: 900 | D8: =B8*C8*1.16 | E8: =D8-B8*C8 | G8: Precio sin iva | H8: Precio con iva
A9: C (Almacenamiento Cloud Storage) | B9: 2 | C9: 250 | D9: =B9*C9*1.16 | E9: =D9-B9*C9 | G9: =H6*2.5 | H9: =G9*1.16
A10: D (API Mensajería Transaccional) | B10: 1 | C10: 266.66667 | D10: =B10*C10*1.16 | E10: =D10-B10*C10
A11: Total Insumos Directos | C11: =SUM(B7*C7, B8*C8, B9*C9, B10*C10) | D11: =SUM(D7:D10) | E11: =SUM(E7:E10)
G12: Ventas (Unidades) | H12: Ingresos con IVA | I12: Costo Asociado | J12: Ganancia Bruta | K12: IVA Trasladado
A13: Capital humano | G13: 1 | H13: =G13*$H$9 | I13: =G13*$H$6 | J13: =H13-I13 | K13: =(H13/1.16)*0.16
A14: Puesto / Especialidad | B14: Plazas | C14: Sueldo bruto | D14: Sueldo - ISR | E14: ISR | G14: 10 | H14: =G14*$H$9 | I14: =G14*$H$6 | J14: =H14-I14 | K14: =(H14/1.16)*0.16
A15: Persona 1 (DevOps y Arquitectura Cloud) | B15: 1 | C15: 7500 | D15: =C15-E15 | E15: 900 | G15: 20 | H15: =G15*$H$9 | I15: =G15*$H$6 | J15: =H15-I15 | K15: =(H15/1.16)*0.16
A16: Persona 2 (Soporte Técnico Almacenes y QA) | B16: 1 | C16: 3333.3333 | D16: =C16-E16 | E16: 400 | G16: 50 | H16: =G16*$H$9 | I16: =G16*$H$6 | J16: =H16-I16 | K16: =(H16/1.16)*0.16
A17: Total Capital Humano | C17: =SUM(C15:C16) | D17: =SUM(D15:D16) | E17: =SUM(E15:E16) | G17: 75 | H17: =G17*$H$9 | I17: =G17*$H$6 | J17: =H17-I17 | K17: =(H17/1.16)*0.16
G18: 100 | H18: =G18*$H$9 | I18: =G18*$H$6 | J18: =H18-I18 | K18: =(H18/1.16)*0.16 | L18: =J18-K18
A19: Servicios mensual | B19: Monto mensual
A20: luz | B20: 600 | G20: IVA PAGADO | H20: IVA COBRADO | I20: IVA SAT (A pagar)
A21: agua | B21: 300 | G21: =E11 | H21: =K18 | I21: =H21-G21
A22: internet | B22: 600
A23: gas (climatización / UPS) | B23: 400
A24: transacciones bancarias y viáticos | B24: 600
A25: Total Servicios | B25: =SUM(B20:B24)
A27: Permisos y Registros
A28: Salubridad (Aviso Privacidad LGPDPPSO) | B28: 1000
A29: protección civil (INDAUTOR y Convenio CUT) | B29: 833.33333
A30: Total Permisos | B30: =SUM(B28:B29)

Sheet Economía de Escala y PE
A1: ANÁLISIS DE ECONOMÍAS DE ESCALA Y DETERMINACIÓN DE PRODUCCIÓN MÍNIMA COMPETITIVA
A2: Demostración de no linealidad del costo y estimación formal del Punto de Equilibrio (Guía BBVA / Baca Urbina)
A4: Costos Fijos Mensuales (CF): | B4: ='Modelo de Costos y Precios'!C17 + 'Modelo de Costos y Precios'!B25 + 'Modelo de Costos y Precios'!B30 | D4: MODELO DE COSTO MEDIO SEGÚN VOLUMEN (ECONOMÍAS DE ESCALA)
A5: • Capital Humano (Dev + Soporte): | B5: ='Modelo de Costos y Precios'!C17 | D5: Volumen (Q) | E5: Costos Fijos | F5: Costos Variables | G5: Costo Total Real | H5: Costo Unitario Real | I5: Precio s/IVA | J5: Utilidad Operativa | K5: Condición
A6: • Servicios Operativos Mensuales: | B6: ='Modelo de Costos y Precios'!B25 | D6: 1 | E6: =$B$4 | F6: =D6*$B$8 | G6: =E6+F6 | H6: =G6/D6 | I6: =$B$9 | J6: =(I6*D6)-G6 | K6: =IF(J6<0, "Déficit / Absorción", IF(D6=35, "Punto Equilibrio", "Rentable (Escala)"))
A7: • Permisos y Trámites Amortizados: | B7: ='Modelo de Costos y Precios'!B30 | D7: 5 | E7: =$B$4 | F7: =D7*$B$8 | G7: =E7+F7 | H7: =G7/D7 | I7: =$B$9 | J7: =(I7*D7)-G7 | K7: =IF(J7<0, "Déficit / Absorción", IF(D7=35, "Punto Equilibrio", "Rentable (Escala)"))
A8: Costo Variable Unitario (CVU) sin IVA: | B8: ='Modelo de Costos y Precios'!C11 / 100 | D8: 10 | E8: =$B$4 | F8: =D8*$B$8 | G8: =E8+F8 | H8: =G8/D8 | I8: =$B$9 | J8: =(I8*D8)-G8 | K8: =IF(J8<0, "Déficit / Absorción", IF(D8=35, "Punto Equilibrio", "Rentable (Escala)"))
A9: Precio de Venta Unitario (P) sin IVA: | B9: ='Modelo de Costos y Precios'!G9 | D9: 20 | E9: =$B$4 | F9: =D9*$B$8 | G9: =E9+F9 | H9: =G9/D9 | I9: =$B$9 | J9: =(I9*D9)-G9 | K9: =IF(J9<0, "Déficit / Absorción", IF(D9=35, "Punto Equilibrio", "Rentable (Escala)"))
A10: Margen de Contribución Unitario (MCU = P - CVU): | B10: =B9 - B8 | D10: 30 | E10: =$B$4 | F10: =D10*$B$8 | G10: =E10+F10 | H10: =G10/D10 | I10: =$B$9 | J10: =(I10*D10)-G10 | K10: =IF(J10<0, "Déficit / Absorción", IF(D10=35, "Punto Equilibrio", "Rentable (Escala)"))
A11: Razón de Margen de Contribución (MCU / P): | B11: =B10 / B9 | D11: 35 | E11: =$B$4 | F11: =D11*$B$8 | G11: =E11+F11 | H11: =G11/D11 | I11: =$B$9 | J11: =(I11*D11)-G11 | K11: =IF(J11<0, "Déficit / Absorción", IF(D11=35, "Punto Equilibrio", "Rentable (Escala)"))
A12: PUNTO DE EQUILIBRIO EN UNIDADES (Q_PE = CF / MCU): | B12: =B4 / B10 | D12: 50 | E12: =$B$4 | F12: =D12*$B$8 | G12: =E12+F12 | H12: =G12/D12 | I12: =$B$9 | J12: =(I12*D12)-G12 | K12: =IF(J12<0, "Déficit / Absorción", IF(D12=35, "Punto Equilibrio", "Rentable (Escala)"))
A13: PUNTO DE EQUILIBRIO EN VENTAS ($): | B13: =B12 * B9 | D13: 75 | E13: =$B$4 | F13: =D13*$B$8 | G13: =E13+F13 | H13: =G13/D13 | I13: =$B$9 | J13: =(I13*D13)-G13 | K13: =IF(J13<0, "Déficit / Absorción", IF(D13=35, "Punto Equilibrio", "Rentable (Escala)"))
D14: 100 | E14: =$B$4 | F14: =D14*$B$8 | G14: =E14+F14 | H14: =G14/D14 | I14: =$B$9 | J14: =(I14*D14)-G14 | K14: =IF(J14<0, "Déficit / Absorción", IF(D14=35, "Punto Equilibrio", "Rentable (Escala)"))

Sheet Criterios y Pareto
A1: EVALUACIÓN MULTICRITERIO Y DIAGRAMA DE PARETO (80/20) DE COSTOS
A2: Criterios analizados: Disponibilidad, Criticidad, Relación Volumen-Precio y Costos Derivados
A4: Partida de Costo | B4: Monto Mensual | C4: % del Total | D4: % Acumulado | E4: Clasificación ABC | F4: Disponibilidad en Mercado | G4: Criticidad Operativa | H4: Sensibilidad al Volumen
A5: Capital Humano Directo (Dev Full-Stack + Soporte) | B5: ='Modelo de Costos y Precios'!C17 | C5: =B5/SUM($B$5:$B$8) | D5: =C5 | E5: A (Crítico 80%) | F5: Media (Talento especializado en cloud/Docker) | G5: Extrema (Desarrollo, seguridad y soporte a planteles) | H5: Baja (Costo fijo mensual independiente del tráfico)
A6: Insumos Cloud / TI (GCP, PostgreSQL, Storage, API) | B6: ='Modelo de Costos y Precios'!D11 | C6: =B6/SUM($B$5:$B$8) | D6: =D5+C6 | E6: A (Crítico 80%) | F6: Inmediata (SLA 99.9% Google Cloud Platform) | G6: Extrema (Disponibilidad de plataforma 24/7) | H6: Alta (Escala linealmente según concurrencia de planteles)
A7: Servicios Operativos (Internet, Luz, Traslados) | B7: ='Modelo de Costos y Precios'!B25 | C7: =B7/SUM($B$5:$B$8) | D7: =D6+C7 | E7: B (Moderado) | F7: Alta (Proveedores de conectividad comercial) | G7: Media (Soporte administrativo y enlace de respaldo) | H7: Baja (Costos base de oficina técnica)
A8: Cumplimiento Legal (LGPDPPSO / INDAUTOR) | B8: ='Modelo de Costos y Precios'!B30 | C8: =B8/SUM($B$5:$B$8) | D8: =D7+C8 | E8: C (Secundario) | F8: Alta (Trámite ante ventanillas oficiales del Estado) | G8: Alta en certeza jurídica, baja en flujo financiero | H8: Nula (Costo de trámite fijo amortizado)
A9: TOTAL COSTO MENSUAL DEL LOTE (100 UNIDADES) | B9: =SUM(B5:B8) | C9: =SUM(C5:C8) | D9: 100.0%

Sheet Cuantificación y Benchmarking
A1: EVALUACIÓN CUANTITATIVA DEL DOLOR OPERATIVO Y BENCHMARKING COMPETITIVO
A2: Cuantificación de mermas/horas-hombre vs. ahorro con SIGRE y análisis comparativo de mercado
A4: A. CUANTIFICACIÓN ANUAL DEL PROBLEMA (PROCESO MANUAL CON VALES DE PAPEL VS. SIGRE)
A5: Parámetro Operativo / Financiero Analizado | B5: Gestión Manual (Vales de Papel) | C5: Gestión Digital con SIGRE | D5: Impacto / Ahorro Generado | E5: Rango de Certeza / Fuente
A6: Transacciones diarias de préstamo promedio (ventanillas de laboratorio) | B6: 300 | C6: 300 | D6: Mismo volumen atendido | E6: Muestreo en CUTonalá / CUCEI
A7: Días hábiles promedio por ciclo académico anual | B7: 200 | C7: 200 | D7: Calendario escolar oficial | E7: Calendario General UdeG
A8: Total anual de solicitudes de préstamo tramitadas | B8: =B6*B7 | C8: =C6*C7 | D8: 60,000 transacciones anuales | E8: Proyección operacional base
A9: Tiempo promedio invertido por transacción de ventanilla (minutos) | B9: 4.5 | C9: 0.45 | D9: -4.05 min (-90.0% de reducción) | E9: Cronometraje en almacén
A10: Horas-hombre totales consumidas al año en ventanilla | B10: =(B8*B9)/60 | C10: =(C8*C9)/60 | D10: 4,050 horas-hombre liberadas | E10: Cálculo derivado
A11: Costo laboral promedio por hora (personal operativo/técnico UdeG) | B11: 110 | C11: 110 | D11: Costo estándar tabular con prestaciones | E11: Tabulador salarial UdeG 2024
A12: Costo anual de nómina absorbido en burocracia de vales | B12: =B10*B11 | C12: =C10*C11 | D12: $445,500.00 MXN en tiempo recuperado | E12: Horas x Costo por hora
A13: Mermas y extravíos anuales de instrumental/equipo no devuelto | B13: 240000 | C13: 12000 | D13: $228,000.00 MXN mitigados (95% control) | E13: Histórico almacén (5% inventario)
A14: Gasto anual en papelería física (vales impresos, carpetas, tóner) | B14: 16500 | C14: 0 | D14: $16,500.00 MXN ahorro en insumos | E14: Presupuesto de compras de insumos
A15: COSTO TOTAL ANUAL DE INEFICIENCIA Y PÉRDIDA POR PLANTEL | B15: =SUM(B12:B14) | C15: =SUM(C12:C14) | D15: =$B$15-$C$15 | E15: Fuga operativa total anual
A16: Costo de Adopción Anual de Licencia SIGRE (1 Almacén Central) | B16: 0 | C16: 28950 | D16: -$28,950.00 MXN inversión anual | E16: Tarifa SaaS anual SIGRE
A17: BENEFICIO NETO ANUAL GENERADO AL CENTRO UNIVERSITARIO | B17: =-B15 | C17: =D15-C16 | D17: $661,050.00 MXN beneficio neto | E17: ROI Operativo: 2,283% | Payback: 15 días
A20: B. ESTUDIO DE MERCADO Y BENCHMARKING COMPETITIVO (SIGRE VS. ALTERNATIVAS)
A21: Criterio / Factor Clave | B21: SIGRE (Propuesta) | C21: ERP Corporativo (SAP Ariba / Oracle) | D21: Software Comercial (Odoo / Zoho) | E21: Gestión Artesanal (Excel / Papel)
A22: Costo Anual de Licenciamiento por Dependencia | B22: $28,950 MXN netos | C22: $220,000 - $480,000 MXN | D22: $65,000 - $110,000 MXN | E22: $0 MXN (Aparente)
A23: Costo y Tiempo de Implementación / Setup | B23: Inmediato (<1 semana, SaaS) | C23: 6 a 12 meses ($350,000+ consultoría) | D23: 2 a 3 meses ($45,000 setup) | E23: Inmediato (sin gobierno ni soporte)
A24: Mecanismo de Contratación Pública en UdeG | B24: Adjudicación Directa (<$200k Art. 55) | C24: Licitación Pública Nacional Obligatoria | D24: Licitación / Invitación Restringida | E24: No aplica
A25: Cumplimiento Normativo LGPDPPSO (Jalisco) | B25: 100% Nativo (Auditoría ITEI / Sujetos Obligados) | C25: Requiere desarrollos y add-ons costosos | D25: Parcial (Enfoque comercial privado) | E25: Nulo (Infracción flagrante por datos expuestos)
A26: Algoritmo Predictivo de Scoring de Fiabilidad | B26: Sí (Calificación dinámica de riesgo del alumno) | C26: No nativo (Requiere módulo BI a la medida) | D26: No disponible en versión estándar | E26: No existe
A27: Modo Operativo Offline en Ventanilla (Contingencia) | B27: Sí (PWA con Service Worker + IndexedDB) | C27: No (Dependencia estricta de red corporativa) | D27: Parcial (App móvil no optimizada a ventanilla) | E27: Papel (Inmune a red, pero sin trazabilidad)
A28: Tiempo Promedio de Despacho en Horas Pico | B28: < 30 segundos (Escaneo QR credencial) | C28: 2 a 3 minutos (Navegación en módulos ERP) | D28: 1 a 2 minutos | E28: 4 a 5 minutos (Llenado y firma de vale)
A29: Enfoque y Adaptabilidad al Entorno Universitario | B29: Específico para almacenes y talleres UdeG | C29: Cadenas de suministro transnacionales | D29: PyME comercial y venta al menudeo | E29: Artesanal e inseguro
A30: Propuesta de Valor Única / Barrera de Entrada | B30: Scoring + LGPDPPSO + Compras Menores UdeG | C30: Ecosistema corporativo integrado | D30: Ecosistema modular de bajo costo | E30: Costo financiero directo cero

Sheet Marco Lógico (MML)
A1: MATRIZ DE MARCO LÓGICO (MML) DEL PROYECTO SIGRE — METODOLOGÍA CEPAL / ILPES
A2: Estructura formal de formulación, objetivos, indicadores verificables y supuestos de sostenibilidad
A4: Nivel de Jerarquía de Objetivos | B4: Resumen Narrativo de Objetivos | C4: Indicadores Objetivamente Verificables (IOV) | D4: Medios de Verificación (MoV) | E4: Supuestos Críticos de Sostenibilidad
A5: FIN | B5: Contribuir a la modernización tecnológica, transparencia en la rendición de cuentas públicas y optimización del gasto operativo en la gestión de materiales, reactivos y equipos en la Red Universitaria de la Universidad de Guadalajara. | C5: 1. Tasa de pérdida o extravío de activos reducida a menos del 0.5% en planteles participantes al término del Año 3. 2. Reducción del 85% en tiempos de espera de alumnos en ventanillas de laboratorios a nivel Red. | D5: Dictámenes telemétricos y reportes de discrepancia cero generados nativamente por SIGRE; actas de cierre semestral de inventario firmadas por las Coordinaciones de Laboratorio de los campus. | E5: La política institucional de la Universidad de Guadalajara mantiene su compromiso estratégico con la política de 'Cero Papel' y la digitalización administrativa.
A6: PROPÓSITO | B6: Optimizar los procesos de solicitud, validación de riesgo, despacho y devolución de inventario en almacenes y ventanillas de centros universitarios (Piloto CUTonalá, expansión a CUCEI y red). | C6: 1. Tiempo promedio de despacho por vale menor a 30 segundos en el 98% de transacciones. 2. 100% de los préstamos cuentan con trazabilidad criptográfica y score de riesgo asignado al solicitante al cierre del Año 1. | D6: Métricas telemétricas de Cloud SQL / BigQuery; reportes mensuales de operación generados automáticamente por SIGRE; bitácoras de auditoría de despacho. | E6: Coordinadores de carrera, laboratoristas y jefes de almacén aplican de forma obligatoria y estandarizada la plataforma en sustitución del vale en papel.
A7: COMPONENTES (PRODUCTOS) | B7: C1. Plataforma Web SaaS multi-tenant en Google Cloud Platform (Cloud Run + PostgreSQL Cloud SQL + Secret Manager). C2. Algoritmo predictivo de Scoring de Fiabilidad del Solicitante. C3. Interfaz de Ventanilla PWA con capacidad de operación en modo offline y sincronización asíncrona. C4. Programa integral de Capacitación, Gobernanza de Datos (LGPDPPSO) y Manuales de Operación. | C7: 1. Disponibilidad de la plataforma de 99.5% mensual (SLA Cloud Run). 2. Capacidad de operación offline local de hasta 4 horas continuas sin conexión a internet. 3. 100% de encargados de ventanilla y jefes de almacén de centros piloto acreditados en el uso del sistema. | D7: Dashboard de monitoreo de Google Cloud Monitoring; reportes de pruebas de carga y estrés k6; actas de acreditación de talleres de capacitación y entrega de manuales. | E7: La infraestructura de Google Cloud Platform mantiene su estándar de estabilidad y el personal operativo muestra adaptabilidad a herramientas digitales.
A8: ACTIVIDADES | B8: A1. Arquitectura de microservicios y despliegue CI/CD en GCP (M1-M2). A2. Desarrollo del motor de scoring y Progressive Web App con Service Workers (M3-M4). A3. Pruebas QA, pentesting OWASP y auditoría LGPDPPSO (M5). A4. Trámite de registro de derechos de autor de software ante INDAUTOR (M6). A5. Despliegue piloto en almacenes y talleres de CUTonalá (M7). A6. Capacitación presencial y marcha blanca con supervisión en sitio (M8-M9). A7. Auditoría técnica, medición de KPIs y release v1.5 para expansión a CUCEI (M10-M12). | C8: 1. Inversión ejecutada conforme al cronograma de $120,000 MXN en Año 1. 2. 100% de los hitos técnicos concluidos en los plazos acordados. 3. Certificado de INDAUTOR obtenido en el Mes 6. | D8: Repositorio de código GitHub con tags de release firmados; comprobante oficial de registro ante INDAUTOR; listas de asistencia a talleres y actas de inicio de piloto. | E8: Los recursos de capital semilla se desembolsan oportunamente y los centros universitarios autorizan el acceso físico y operativo a almacenes para la implementación.

Sheet Cronograma e Inversión Año 1
A1: CRONOGRAMA DETALLADO DE EJECUCIÓN (DIAGRAMA DE GANTT) Y ABSORCIÓN DE CAPITAL — AÑO 1
A2: Programación mensual de hitos críticos: Desarrollo, QA, Trámite INDAUTOR, Piloto CUTonalá y Capacitación (Meses 1 a 12)
A4: Fase / Actividad Crítica | B4: Responsable Operativo | C4: M1 | D4: M2 | E4: M3 | F4: M4 | G4: M5 | H4: M6 | I4: M7 | J4: M8 | K4: M9 | L4: M10 | M4: M11 | N4: M12 | O4: Presupuesto Partida
A5: 1. Arquitectura Cloud GCP y Microservicios Base (Cloud Run, PostgreSQL) | B5: Lead DevOps | C5: ● | D5: ● | O5: 24000
A6: 2. Motor Algorítmico de Scoring de Riesgo y PWA Offline con Service Workers | B6: Dev Full-Stack | E6: ● | F6: ● | O6: 25000
A7: 3. Pruebas Unitarias, Integración, Estrés de Carga (k6) y Auditoría LGPDPPSO | B7: QA Engineer | G7: ● | O7: 12000
A8: 4. Hito Legal: Trámite Registro Software INDAUTOR (Buffer 3 sem) | B8: Asesor Jurídico / PM | H8: ● | O8: 5500
A9: 5. Despliegue Piloto en CUTonalá (Almacén Central y Laboratorios de Cómputo) | B9: DevOps + Soporte | I9: ● | O9: 11500
A10: 6. Programa de Capacitación Presencial a Almacenistas y Laboratoristas | B10: Customer Success / Soporte | J10: ● | K10: ● | O10: 10000
A11: 7. Marcha Blanca y Monitoreo de KPIs Ventanilla (Buffer 2 sem) | B11: Soporte L2 | K11: ● | L11: ● | M11: ● | O11: 16500
A12: 8. Evaluación de Impacto, Release v1.5 y Preparación Expansión hacia CUCEI | B12: Equipo Completo | N12: ● | O12: 15500
A13: ABSORCIÓN PRESUPUESTAL MENSUAL ESTIMADA (MXN) | B13: Total por Mes | C13: 12000 | D13: 12000 | E13: 12500 | F13: 12500 | G13: 12000 | H13: 5500 | I13: 11500 | J13: 5000 | K13: 10500 | L13: 5500 | M13: 5500 | N13: 15500 | O13: =SUM(O5:O12)

Sheet Estado de Resultados Pro Forma
A1: ESTADO DE RESULTADOS PROYECTADO PRO FORMA — HORIZONTE A 3 AÑOS (MXN)
A2: Proyección contable bajo supuestos de adopción escalonada: Piloto CUTonalá (Año 1), Expansión CUCEI (Año 2) y Consolidación Red (Año 3)
A4: Concepto Contable / Financiero | B4: Año 1 (Piloto CUTonalá - 5 deps) | C4: Año 2 (Expansión CUCEI - 25 deps) | D4: Año 3 (Consolidación Red - 100 deps) | E4: Notas Técnicas y Criterios Contables
A5: Dependencias Universitarias Contratadas | B5: 5 | C5: 25 | D5: 100 | E5: Almacenes y laboratorios de centros universitarios
A6: Precio de Venta Anual por Dependencia (sin IVA) | B6: 28950 | C6: 28950 | D6: 28950 | E6: Tarifa fija anualizada ($2,412.50 MXN / mes neto)
A7: INGRESOS BRUTOS OPERACIONALES | B7: =B5*B6 | C7: =C5*C6 | D7: =D5*D6 | E7: Facturación por servicios SaaS institucional
A8: Descuentos y Devoluciones Comerciales (0%) | B8: 0 | C8: 0 | D8: 0 | E8: Contratación directa anual fija
A9: INGRESOS NETOS OPERACIONALES | B9: =B7-B8 | C9: =C7-C8 | D9: =D7-D8 | E9: Base gravable neta operacional
A10: Costo del Servicio / Servidores Cloud GCP (Costo Variable) | B10: 6120 | C10: 30600 | D10: 122400 | E10: Consumo de Cloud Run, Cloud SQL, Storage ($102 MXN/dep/mes x12)
A11: UTILIDAD BRUTA | B11: =B9-B10 | C11: =C9-C10 | D11: =D9-D10 | E11: Margen de contribución total
A12: Margen Bruto (%) | B12: =B11/B9 | C12: =C11/C9 | D12: =D11/D9 | E12: Margen bruto SaaS típicamente >90%
A13: GASTOS DE OPERACIÓN Y ADMINISTRACIÓN: | E13: Costos fijos operacionales y talento humano
A14: • Nómina y Honorarios Técnicos (DevOps, QA, Soporte N1/N2) | B14: 126000 | C14: 252000 | D14: 540000 | E14: Evolución de organigrama: 2 perfiles A1 -> 3 A2 -> 5 A3
A15: • Conectividad, Licencias de Desarrollo y Oficina Técnica | B15: 18000 | C15: 36000 | D15: 72000 | E15: Herramientas de monitoreo, repositorios y oficina
A16: • Viáticos, Talleres y Capacitación Presencial en Campus | B16: 8500 | C16: 22000 | D16: 45000 | E16: Onboarding y sesiones prácticas en almacenes
A17: • Trámites Legales, Contabilidad y Registro INDAUTOR | B17: 5500 | C17: 12000 | D17: 25000 | E17: Registro de software en A1, compliance legal continuo
A18: TOTAL GASTOS DE OPERACIÓN | B18: =SUM(B14:B17) | C18: =SUM(C14:C17) | D18: =SUM(D14:D17) | E18: Total OPEX anual
A19: UTILIDAD DE OPERACIÓN / EBITDA | B19: =B11-B18 | C19: =C11-C18 | D19: =D11-D18 | E19: Flujo operacional antes de impuestos
A20: Margen Operativo (%) | B20: =B19/B9 | C20: =C19/C9 | D20: =D19/D9 | E20: Rentabilidad sobre ventas brutas
A21: Impuesto Sobre la Renta (ISR Estimado 30%) | B21: =IF(B19>0, B19*0.30, 0) | C21: =IF(C19>0, C19*0.30, 0) | D21: =IF(D19>0, D19*0.30, 0) | E21: Tasa corporativa estándar (sin base gravable en déficit)
A22: UTILIDAD (PÉRDIDA) NETA PROYECTADA | B22: =B19-B21 | C22: =C19-C21 | D22: =D19-D21 | E22: Resultado neto final del ejercicio
A23: Margen Neto (%) | B23: =B22/B9 | C23: =C22/C9 | D23: =D22/D9 | E23: Rentabilidad neta final

Sheet Flujo de Efectivo Mensual
A1: FLUJO DE EFECTIVO MENSUAL PRO FORMA (CASH FLOW) — AÑO 1 PILOTO (MXN)
A2: Análisis de liquidez mensual, absorción de capital semilla de $120,000 MXN y tasa de quema de efectivo (burn rate)
A4: Concepto de Flujo de Efectivo | B4: M1 | C4: M2 | D4: M3 | E4: M4 | F4: M5 | G4: M6 | H4: M7 | I4: M8 | J4: M9 | K4: M10 | L4: M11 | M4: M12 | N4: Total Año 1
A5: SALDO INICIAL DE EFECTIVO EN CAJA | B5: 0 | C5: =B18 | D5: =C18 | E5: =D18 | F5: =E18 | G5: =F18 | H5: =G18 | I5: =H18 | J5: =I18 | ... M5: =L18 | N5: =B5
A6: ENTRADAS DE EFECTIVO OPERATIVAS Y FINANCIAMIENTO:
A7: • Aportación de Capital Semilla Inicial | B7: 120000 | C7: 0 | D7: 0 | E7: 0 | F7: 0 | G7: 0 | H7: 0 | I7: 0 | J7: 0 | K7: 0 | L7: 0 | M7: 0 | N7: =SUM(B7:M7)
A8: • Cobranza de Licencias Piloto CUTonalá (5 deps + IVA) | B8: 0 | C8: 0 | D8: 0 | E8: 0 | F8: 0 | G8: 0 | H8: 167910 | I8: 0 | J8: 0 | K8: 0 | L8: 0 | M8: 0 | N8: =SUM(B8:M8)
A9: TOTAL ENTRADAS DE EFECTIVO | B9: =SUM(B7:B8) | C9: =SUM(C7:C8) | D9: =SUM(D7:D8) | E9: =SUM(E7:E8) | F9: =SUM(F7:F8) | G9: =SUM(G7:G8) | H9: =SUM(H7:H8) | I9: =SUM(I7:I8) | ... N9: =SUM(N7:N8)
A10: SALIDAS DE EFECTIVO OPERATIVAS (EGRESOS):
A11: • Nómina y Honorarios Técnicos (DevOps + QA) | B11: 10500 | C11: 10500 | D11: 10500 | E11: 10500 | F11: 10500 | G11: 10500 | H11: 10500 | I11: 10500 | J11: 10500 | K11: 10500 | L11: 10500 | M11: 10500 | N11: =SUM(B11:M11)
A12: • Servicios Cloud GCP (Compute, SQL, Storage) | B12: 510 | C12: 510 | D12: 510 | E12: 510 | F12: 510 | G12: 510 | H12: 510 | I12: 510 | J12: 510 | K12: 510 | L12: 510 | M12: 510 | N12: =SUM(B12:M12)
A13: • Conectividad, Licencias Dev y Soporte Base | B13: 990 | C13: 990 | D13: 1490 | E13: 1490 | F13: 990 | G13: 0 | H13: 400 | I13: 0 | J13: 0 | K13: 0 | L13: 0 | M13: 0 | N13: =SUM(B13:M13)
A14: • Registro de Obra Software ante INDAUTOR (Hito M6) | B14: 0 | C14: 0 | D14: 0 | E14: 0 | F14: 0 | G14: 3500 | H14: 0 | I14: 0 | J14: 0 | K14: 0 | L14: 0 | M14: 0 | N14: =SUM(B14:M14)
A15: • Viáticos y Talleres de Capacitación en Almacenes | B15: 0 | C15: 0 | D15: 0 | E15: 0 | F15: 0 | G15: 0 | H15: 2590 | I15: 2500 | J15: 0 | K15: 0 | L15: 0 | M15: 0 | N15: =SUM(B15:M15)
A16: • Auditoría Técnica, Evaluación Piloto y Cierre v1.5 | B16: 0 | C16: 0 | D16: 0 | E16: 0 | F16: 0 | G16: 0 | H16: 0 | I16: 0 | J16: 0 | K16: 0 | L16: 0 | M16: 4490 | N16: =SUM(B16:M16)
A17: TOTAL SALIDAS DE EFECTIVO | B17: =SUM(B11:B16) | C17: =SUM(C11:C16) | D17: =SUM(D11:D16) | E17: =SUM(E11:E16) | F17: =SUM(F11:F16) | G17: =SUM(G11:G16) | H17: =SUM(H11:H16) | I17: =SUM(I11:I16) | ... N17: =SUM(N11:N16)
A18: SALDO FINAL ACUMULADO EN CAJA (TESORERÍA) | B18: =B5+B9-B17 | C18: =C5+C9-C17 | D18: =D5+D9-D17 | E18: =E5+E9-E17 | F18: =F5+F9-F17 | G18: =G5+G9-G17 | H18: =H5+H9-H17 | I18: =I5+I9-I17 | ... M18: =M5+M9-M17 | N18: =M18
A19: FLUJO NETO MENSUAL (Entradas - Salidas) | B19: =B9-B17 | C19: =C9-C17 | D19: =D9-D17 | E19: =E9-E17 | F19: =F9-F17 | G19: =G9-G17 | H19: =H9-H17 | I19: =I9-I17 | ... N19: =N9-N17
A22: INDICADORES CLAVE DE TESORERÍA Y RIESGO FINANCIERO
A23: Tasa de Quema de Efectivo Promedio (Burn Rate Pre-operativo M1-M6) | B23: $12,583 MXN / mes | C23: Gasto neto de operación mensual previo al cobro de licencias
A24: Punto Mínimo de Tesorería en Caja (Mes 6 - Hito INDAUTOR) | B24: $44,500 MXN | C24: Colchón mínimo de seguridad antes de la facturación del piloto (37% de capital intacto)
A25: Requerimiento Máximo de Capital de Trabajo (Inversión Inicial) | B25: $120,000 MXN | C25: Monto suficiente para garantizar solvencia operativa del 100%
A26: Superávit de Caja al Cierre del Año 1 | B26: $136,350 MXN | C26: Fondo de reserva disponible para financiar la expansión en CUCEI

Sheet Análisis de Sensibilidad
A1: ANÁLISIS DE SENSIBILIDAD FINANCIERA Y ESTRÉS DE TESORERÍA — PROYECTO SIGRE
A2: Simulación de resiliencia: Escenario Base, Pesimista Cambiario (+15% GCP) y Pesimista Comercial (Retraso 4 meses de cobranza)
A4: A. COMPARACIÓN DE ESCENARIOS DE ESTRÉS OPERATIVO Y FINANCIERO (AÑO 1)
A5: Parámetro Financiero / Métrica Clave | B5: Escenario Base (Esperado) | C5: Escenario Pesimista Cambiario (+15% GCP) | D5: Escenario Pesimista Comercial (Retraso 4 Meses) | E5: Evaluación de Resiliencia / Diagnóstico
A6: Dependencias Contratadas en Año 1 | B6: 5 dependencias | C6: 5 dependencias | D6: 5 dependencias | E6: Mismo alcance piloto CUTonalá
A7: Mes de Cobranza Efectiva de Contratos | B7: Mes 7 (Arranque Piloto) | C7: Mes 7 (Arranque Piloto) | D7: Mes 11 (Retraso de 4 meses de firmas) | E7: Estrés de morosidad administrativa universitaria
A8: Ingresos Totales con IVA Año 1 | B8: $167,910.00 | C8: $167,910.00 | D8: $167,910.00 | E8: Facturación íntegra de 5 dependencias contratadas
A9: Costo Anual Infraestructura Cloud GCP | B9: $6,120.00 | C9: $7,038.00 | D9: $6,120.00 | E9: +15% por paridad peso/dólar en Google Cloud
A10: Margen Bruto de Servicio (%) | B10: 95.8% | C10: 95.1% | D10: 95.8% | E10: Impacto marginal que no compromete rentabilidad
A11: Gastos Operativos Fijos y Trámites | B11: $145,440.00 | C11: $145,440.00 | D11: $145,440.00 | E11: Nóminas técnicas y registro de obra INDAUTOR
A12: Total Egresos Operativos Año 1 | B12: $151,560.00 | C12: $152,478.00 | D12: $151,560.00 | E12: Incremento máximo de $918 MXN en todo el año
A13: Tasa de Quema de Efectivo (Burn Rate Pre-op) | B13: $12,583.33 / mes | C13: $12,660.00 / mes | D13: $12,583.33 / mes | E13: Gasto mensual neto estrictamente controlado
A14: PUNTO MÍNIMO DE TESORERÍA EN CAJA | B14: $44,500.00 (Mes 6) | C14: $43,962.00 (Mes 6) | D14: $7,470.00 (Mes 10) | E14: Caja SIEMPRE positiva: resiste 4 meses de mora
A15: Colchón Mínimo de Seguridad (% Capital) | B15: 37.1% | C15: 36.6% | D15: 6.2% | E15: Resiste demoras de firmas sin caer en insolvencia
A16: SUPERÁVIT FINAL EN CAJA AL CIERRE DE AÑO 1 | B16: $136,380.00 | C16: $135,462.00 | D16: $136,380.00 | E16: Solvencia asegurada para expansión en CUCEI
A19: B. REQUERIMIENTOS TÉCNICOS DE VENTANILLA Y MÉTRICAS DE SATURACIÓN DE SOPORTE
A20: Componente / Dimensión | B20: Requerimiento Técnico Mínimo en Ventanilla | C20: Métrica / Umbral de Saturación | D20: Impacto en SLA y Mitigación de Riesgo
A21: Hardware de Cómputo en Ventanilla | B21: CPU 2 núcleos 2.0 GHz (Core i3 4ª gen / AMD Ryzen 3), 4 GB RAM, 500 MB libres | C21: Compatibilidad con el 98% del parque instalado en UdeG | D21: Asegura ejecución ágil de PWA con IndexedDB y AES-256 sin retardo
A22: Navegador y Conectividad | B22: Google Chrome v90+, Firefox v88+ o Edge v90+ (con Service Workers) | C22: Soporte obligatorio de Background Sync API y almacenamiento local | D22: Garantiza el modo contingencia offline ininterrumpido en horas pico
A23: Periféricos de Captura | B23: Lector óptico USB de código de barras/QR (Plug & Play) o webcam 720p | C23: Lectura en <1 segundo por credencial | D23: Reduce el tiempo de atención de 4.5 min a <27 segundos
A24: Umbral de Contratación Soporte N1 (Escala) | B24: Alcanzar 15 dependencias universitarias activas concurrentes | C24: Métrica de saturación comercial (Trigger Fase 2) | D24: Evita sobrecargar al Lead DevOps y asegura SLA de respuesta <15 min
A25: Umbral de Contratación Soporte N1 (Carga) | B25: > 20 tickets semanales durante dos semanas consecutivas o respuesta L2 > 25 min | C25: Métrica de saturación operativa de Mesa de Ayuda | D25: Garantiza resolución de fallas críticas en <1 hora en ventanillas
